README.rst
setup.py
scripts/tatorter
scripts/tatorter.py
src/tatorter.egg-info/PKG-INFO
src/tatorter.egg-info/SOURCES.txt
src/tatorter.egg-info/dependency_links.txt
src/tatorter.egg-info/pbr.json
src/tatorter.egg-info/requires.txt
src/tatorter.egg-info/top_level.txt
src/tatorterp/__init__.py
src/tatorterp/cli.py
src/tatorterp/grabber.py