Metadata-Version: 1.1
Name: tatorter
Version: 0.1.5
Summary: A simple script to rename Tatort episode video files to a unique pattern.
Home-page: UNKNOWN
Author: DLFW
Author-email: UNKNOWN
License: GPL 3
Platform: UNKNOWN
Classifier: Environment :: Console
Classifier: License :: OSI Approved :: GNU General Public License v3 (GPLv3)
